serialize/__init__.py
serialize/serializes.py
flask_simpleserialize-0.0.3.dist-info/LICENSE
flask_simpleserialize-0.0.3.dist-info/METADATA
flask_simpleserialize-0.0.3.dist-info/WHEEL
flask_simpleserialize-0.0.3.dist-info/top_level.txt
flask_simpleserialize-0.0.3.dist-info/RECORD
