Metadata-Version: 2.1
Name: flask-simpleserialize
Version: 0.0.3
Summary: 一个针对于flask框架的序列化工具
Home-page: https://github.com/pypa/sampleproject
Author: 张斌
Author-email: 786017877@163.com
License: UNKNOWN
Platform: UNKNOWN
Classifier: Programming Language :: Python :: 3
Classifier: License :: OSI Approved :: MIT License
Classifier: Operating System :: OS Independent
License-File: LICENSE
